cvvdp-0.5.4.dist-info/licenses/LICENSE
pycvvdp/__init__.py
pycvvdp/csf.py
pycvvdp/cvvdp_metric.py
pycvvdp/cvvdp_ml_metric.py
pycvvdp/display_model.py
pycvvdp/dm_preview_metric.py
pycvvdp/dump_channels.py
pycvvdp/interp.py
pycvvdp/lpyr_dec.py
pycvvdp/psnr_metric.py
pycvvdp/run_cvvdp.py
pycvvdp/ssim_metric.py
pycvvdp/test_masking.py
pycvvdp/utils.py
pycvvdp/video_source.py
pycvvdp/video_source_file.py
pycvvdp/video_source_yuv.py
pycvvdp/video_writer.py
pycvvdp/visualize_diff_map.py
pycvvdp/vq_metric.py
pycvvdp/csf_cache/o0_sn1_5_cm0_604562_gpu0.mat
pycvvdp/csf_cache/o5_sn1_5_cm0_604562_gpu0.mat
pycvvdp/third_party/__init__.py
pycvvdp/third_party/cpuinfo.py
pycvvdp/third_party/loadmat.py
pycvvdp/third_party/ssim.py
pycvvdp/vvdp_data/README.md
pycvvdp/vvdp_data/color_spaces.json
pycvvdp/vvdp_data/csf_lut_dkl_cone.json
pycvvdp/vvdp_data/csf_lut_log.json
pycvvdp/vvdp_data/csf_lut_none.json
pycvvdp/vvdp_data/csf_lut_weber.json
pycvvdp/vvdp_data/csf_lut_weber_fixed_size.json
pycvvdp/vvdp_data/csf_lut_weber_old.json
pycvvdp/vvdp_data/csf_lut_weber_supra.json
pycvvdp/vvdp_data/cvvdp_parameters.json
pycvvdp/vvdp_data/display_models.json
pycvvdp/vvdp_data/cvvdp_ml_saliency/cvvdp_parameters.json
pycvvdp/vvdp_data/cvvdp_ml_transformer/cvvdp_parameters.json
cvvdp-0.5.4.dist-info/METADATA
cvvdp-0.5.4.dist-info/WHEEL
cvvdp-0.5.4.dist-info/entry_points.txt
cvvdp-0.5.4.dist-info/top_level.txt
cvvdp-0.5.4.dist-info/RECORD
