Metadata-Version: 2.4
Name: cvvdp
Version: 0.5.4
Summary: PyTorch code for 'ColorVideoVDP': a full-reference visual quality metric that predicts the perceptual difference between pairs of images or videos.
Maintainer-email: Rafał Mantiuk <mantiuk@gmail.com>
License-Expression: MIT
Project-URL: Homepage, https://github.com/gfxdisp/ColorVideoVDP
Project-URL: Issues, https://github.com/gfxdisp/ColorVideoVDP/issues
Classifier: Development Status :: 3 - Alpha
Classifier: Intended Audience :: Science/Research
Classifier: Operating System :: OS Independent
Classifier: Programming Language :: Python :: 3.8
Classifier: Programming Language :: Python :: 3.9
Classifier: Programming Language :: Python :: 3.10
Classifier: Programming Language :: Python :: 3.11
Requires-Python: >=3.8
License-File: LICENSE
Requires-Dist: numpy>=1.17.3
Requires-Dist: scipy>=1.10.0
Requires-Dist: ffmpeg-python>=0.2.0
Requires-Dist: torch>=1.13.1
Requires-Dist: torchvision>=0.9.2
Requires-Dist: ffmpeg>=1.4
Requires-Dist: imageio>=2.19.5
Requires-Dist: matplotlib>=3.8.0
Requires-Dist: huggingface_hub>=0.33.4
Requires-Dist: einops>=0.8.1
Requires-Dist: PyEXR>=0.3.10
Requires-Dist: nvidia-ml-py
Dynamic: license-file
